compas_igs/__init__.py
compas_igs/__main__.py
compas_igs/activate.py
compas_igs/install.py
compas_igs/rhino/__init__.py
compas_igs/rhino/diagramartist.py
compas_igs/rhino/diagramobject.py
compas_igs/rhino/forceartist.py
compas_igs/rhino/forceinspector.py
compas_igs/rhino/forceobject.py
compas_igs/rhino/formartist.py
compas_igs/rhino/forminspector.py
compas_igs/rhino/formobject.py
compas_igs/rhino/scene.py
compas_igs/rhino/settings.py
compas_igs/rhino/unifieddiagram.py
compas_igs/rhino/forms/__init__.py
compas_igs/rhino/forms/attributesform.py
compas_igs/rhino/forms/browser.py
compas_igs/rhino/forms/src/background.png
compas_igs/rhino/forms/src/brg.png
compas_igs/rhino/forms/src/eth.png
compas_igs/rhino/forms/src/igs.png
compas_igs/rhino/forms/src/index.html
compas_igs/rhino/forms/src/styles.css
compas_igs/ui/Rhino/IGS/dev/IGS.rui
compas_igs/ui/Rhino/IGS/dev/IGS__init_cmd.py
compas_igs/ui/Rhino/IGS/dev/IGS__redo_cmd.py
compas_igs/ui/Rhino/IGS/dev/IGS__restart_cmd.py
compas_igs/ui/Rhino/IGS/dev/IGS__undo_cmd.py
compas_igs/ui/Rhino/IGS/dev/IGS_constraint_table_cmd.py
compas_igs/ui/Rhino/IGS/dev/IGS_docs_cmd.py
compas_igs/ui/Rhino/IGS/dev/IGS_edge_information_cmd.py
compas_igs/ui/Rhino/IGS/dev/IGS_edges_table_cmd.py
compas_igs/ui/Rhino/IGS/dev/IGS_force_constraint_vertex_cmd.py
compas_igs/ui/Rhino/IGS/dev/IGS_force_displaysettings_cmd.py
compas_igs/ui/Rhino/IGS/dev/IGS_force_from_form_cmd.py
compas_igs/ui/Rhino/IGS/dev/IGS_force_inspector_control_cmd.py
compas_igs/ui/Rhino/IGS/dev/IGS_force_inspector_off_cmd.py
compas_igs/ui/Rhino/IGS/dev/IGS_force_inspector_on_cmd.py
compas_igs/ui/Rhino/IGS/dev/IGS_force_move_cmd.py
compas_igs/ui/Rhino/IGS/dev/IGS_force_move_nodes_cmd.py
compas_igs/ui/Rhino/IGS/dev/IGS_force_scale_cmd.py
compas_igs/ui/Rhino/IGS/dev/IGS_force_select_anchor_cmd.py
compas_igs/ui/Rhino/IGS/dev/IGS_force_select_fixed_cmd.py
compas_igs/ui/Rhino/IGS/dev/IGS_force_update_cmd.py
compas_igs/ui/Rhino/IGS/dev/IGS_form_assign_forces_cmd.py
compas_igs-0.3.4.dist-info/AUTHORS.md
compas_igs-0.3.4.dist-info/LICENSE
compas_igs-0.3.4.dist-info/METADATA
compas_igs-0.3.4.dist-info/WHEEL
compas_igs-0.3.4.dist-info/entry_points.txt
compas_igs-0.3.4.dist-info/top_level.txt
compas_igs-0.3.4.dist-info/RECORD
