Metadata-Version: 2.1
Name: compas-igs
Version: 0.3.4
Summary: IGS is an implementation of  for Rhino 6+
Home-page: https://github.com/BlockResearchGroup/compas_igs
Author: Ricardo Maia Avelino
Author-email: maia@arch.ethz.ch
License: MIT license
Platform: UNKNOWN
Classifier: Development Status :: 4 - Beta
Classifier: Intended Audience :: Developers
Classifier: Topic :: Scientific/Engineering
Classifier: License :: OSI Approved :: MIT License
Classifier: Operating System :: Unix
Classifier: Operating System :: POSIX
Classifier: Operating System :: Microsoft :: Windows
Classifier: Programming Language :: Python
Classifier: Programming Language :: Python :: 3
Classifier: Programming Language :: Python :: 3.6
Classifier: Programming Language :: Python :: 3.7
Classifier: Programming Language :: Python :: 3.8
Classifier: Programming Language :: Python :: Implementation :: CPython
Requires-Python: >=3.6
License-File: LICENSE
License-File: AUTHORS.md
Requires-Dist: compas (>=1.9.4)
Requires-Dist: compas-ags
